taxicab/__init__.py
taxicab/_about.py
taxicab/_api.py
taxicab/distance.py
taxicab/plot.py
taxicab-0.1.1.dist-info/LICENSE
taxicab-0.1.1.dist-info/METADATA
taxicab-0.1.1.dist-info/WHEEL
taxicab-0.1.1.dist-info/top_level.txt
taxicab-0.1.1.dist-info/RECORD
