Metadata-Version: 2.2
Name: Taxicab
Version: 0.1.1
Summary: Accurate routing for Open Street Maps and OSMnx
Author-email: Nathan Rooy <nathanrooy@gmail.com>
License: MIT License
Project-URL: Code, https://github.com/nathanrooy/taxicab
Project-URL: Issues, https://github.com/nathanrooy/taxicab/issues
Classifier: Programming Language :: Python :: 3
Classifier: License :: OSI Approved :: MIT License
Classifier: Operating System :: OS Independent
Classifier: Programming Language :: Python
Classifier: Programming Language :: Python :: 3
Classifier: Programming Language :: Python :: 3 :: Only
Classifier: Programming Language :: Python :: 3.9
Classifier: Programming Language :: Python :: 3.10
Classifier: Programming Language :: Python :: 3.11
Classifier: Programming Language :: Python :: 3.12
Classifier: Programming Language :: Python :: 3.13
Classifier: Topic :: Scientific/Engineering :: GIS
Classifier: Topic :: Scientific/Engineering :: Information Analysis
Classifier: Topic :: Scientific/Engineering :: Mathematics
Requires-Python: >=3.5
License-File: LICENSE
Requires-Dist: matplotlib>=3.3.0
Requires-Dist: networkx>=2.5
Requires-Dist: numpy>=1.19
Requires-Dist: osmnx>=2.0.1
Requires-Dist: Shapely>=1.7
